termate/__init__.py
termate/app.py
termate/utils/__init__.py
termate/utils/bcolors.py
termate/utils/openRouterClient.py
termate/utils/processCommand.py
termate/utils/runCommand.py
termate/utils/userCLI.py
termate_ai-0.1.0.dist-info/licenses/LICENSE
termate_ai-0.1.0.dist-info/METADATA
termate_ai-0.1.0.dist-info/WHEEL
termate_ai-0.1.0.dist-info/entry_points.txt
termate_ai-0.1.0.dist-info/top_level.txt
termate_ai-0.1.0.dist-info/RECORD
